biseau_gui/__init__.py
biseau_gui/__main__.py
biseau_gui/aspviewer.py
biseau_gui/dotviewer.py
biseau_gui/imageviewer.py
biseau_gui/logwidget.py
biseau_gui/mainwindow.py
biseau_gui/modelsviewer.py
biseau_gui/openscriptwidget.py
biseau_gui/optionswidget.py
biseau_gui/output_exporter.py
biseau_gui/qtutils.py
biseau_gui/script_exporter.py
biseau_gui/scriptbrowser.py
biseau_gui/scripteditor.py
biseau_gui/scriptlistwidget.py
biseau_gui/embedded_contexts/dns.lp
biseau_gui/embedded_contexts/human.cxt
biseau_gui/embedded_contexts/lattice.cxt
biseau_gui/embedded_contexts/liveinwater.txt
biseau_gui/embedded_contexts/metabolic-network-ex1.lp
biseau_gui/embedded_contexts/numbers.lp
biseau_gui/embedded_contexts/relations.csv
biseau_gui/embedded_contexts/tealady.cxt
biseau_gui/embedded_contexts/vowels.csv
biseau_gui/embedded_scripts/ASPExtractor.py
biseau_gui/embedded_scripts/black_theme.json
biseau_gui/embedded_scripts/blank.lp
biseau_gui/embedded_scripts/build_concepts.py
biseau_gui/embedded_scripts/build_concepts_simple.py
biseau_gui/embedded_scripts/build_galois_lattice.json
biseau_gui/embedded_scripts/build_iceberg_lattice.py
biseau_gui/embedded_scripts/complex-labelling.lp
biseau_gui/embedded_scripts/compute_score.py
biseau_gui/embedded_scripts/context.py
biseau_gui/embedded_scripts/default.lp
biseau_gui/embedded_scripts/example.py
biseau_gui/embedded_scripts/fca_concepts.lp
biseau_gui/embedded_scripts/fca_lattice.lp
biseau_gui/embedded_scripts/metabolic_network_seed_search.py
biseau_gui/embedded_scripts/open_data.py
biseau_gui/embedded_scripts/pattern_structure.py
biseau_gui/embedded_scripts/raw_data.lp
biseau_gui/embedded_scripts/rdf_query_example.json
biseau_gui/embedded_scripts/rdf_shower.json
biseau_gui/embedded_scripts/record-example.lp
biseau_gui/embedded_scripts/record.py
biseau_gui/embedded_scripts/render-metabolic-network.lp
biseau_gui/embedded_scripts/render_interactions.json
biseau_gui/embedded_scripts/show_galois_lattice.py
biseau_gui-0.0.6.dist-info/METADATA
biseau_gui-0.0.6.dist-info/WHEEL
biseau_gui-0.0.6.dist-info/top_level.txt
biseau_gui-0.0.6.dist-info/RECORD
